LICENSE
MANIFEST.in
README.md
setup.py
django_rolodex.egg-info/PKG-INFO
django_rolodex.egg-info/SOURCES.txt
django_rolodex.egg-info/dependency_links.txt
django_rolodex.egg-info/requires.txt
django_rolodex.egg-info/top_level.txt
rolodex/__init__.py
rolodex/admin.py
rolodex/forms.py
rolodex/models.py
rolodex/routers.py
rolodex/settings.py
rolodex/slug.py
rolodex/tests.py
rolodex/urls.py
rolodex/views.py
rolodex/API/__init__.py
rolodex/API/__init__.pyc
rolodex/API/router.py
rolodex/API/router.pyc
rolodex/API/serializers.py
rolodex/API/serializers.pyc
rolodex/API/views.py
rolodex/API/views.pyc
rolodex/fixtures/rolodex_models_testdata.json
rolodex/fixtures/rolodex_views_testdata.json
rolodex/migrations/0001_initial.py
rolodex/migrations/0001_initial.pyc
rolodex/migrations/0002_fixtures.py
rolodex/migrations/0002_fixtures.pyc
rolodex/migrations/__init__.py
rolodex/migrations/__init__.pyc
rolodex/static/rolodex/css/ajax_select.css
rolodex/static/rolodex/css/base.css
rolodex/static/rolodex/css/bootstrap.css
rolodex/static/rolodex/css/entity.css
rolodex/static/rolodex/css/entity_map.css
rolodex/static/rolodex/css/home.css
rolodex/static/rolodex/css/jquery-ui-.min.css
rolodex/static/rolodex/css/jquery-ui.min.css
rolodex/static/rolodex/css/jquery-ui.min2.css
rolodex/static/rolodex/css/new_entity.css
rolodex/static/rolodex/css/new_relation.css
rolodex/static/rolodex/css/nodeMap.css
rolodex/static/rolodex/css/selectize.css
rolodex/static/rolodex/css/toggle.css
rolodex/static/rolodex/fonts/glyphicons-halflings-regular.eot
rolodex/static/rolodex/fonts/glyphicons-halflings-regular.svg
rolodex/static/rolodex/fonts/glyphicons-halflings-regular.ttf
rolodex/static/rolodex/fonts/glyphicons-halflings-regular.woff
rolodex/static/rolodex/images/card.png
rolodex/static/rolodex/images/dmnlogo.jpg
rolodex/static/rolodex/images/reaper.png
rolodex/static/rolodex/images/spinner.gif
rolodex/static/rolodex/images/waiting.gif
rolodex/static/rolodex/images/favicon/android-icon-144x144.png
rolodex/static/rolodex/images/favicon/android-icon-192x192.png
rolodex/static/rolodex/images/favicon/android-icon-36x36.png
rolodex/static/rolodex/images/favicon/android-icon-48x48.png
