Metadata-Version: 1.1
Name: django-rolodex
Version: 0.1.3.3
Summary: A Django app for managing relationships between people and organizations.
Home-page: https://github.com/DallasMorningNews/django-rolodex/
Author: Jon McClure
Author-email: jon.r.mcclure@gmail.com
License: MIT License
Platform: UNKNOWN
Classifier: Development Status :: 3 - Alpha
Classifier: Environment :: Web Environment
Classifier: Framework :: Django
Classifier: Intended Audience :: Developers
Classifier: License :: OSI Approved :: MIT License
Classifier: Operating System :: OS Independent
Classifier: Programming Language :: Python
Classifier: Programming Language :: Python :: 2.6
Classifier: Programming Language :: Python :: 2.7
Classifier: Topic :: Internet :: WWW/HTTP
Classifier: Topic :: Internet :: WWW/HTTP :: Dynamic Content
